app/__init__.py
app/skyspark/__init__.py
app/skyspark/client.py
app/skyspark/converters.py
app/skyspark/grid.py
app/skyspark/types.py
app/tools/__init__.py
app/tools/axon_tools.py
skyforge_mcp-0.1.0.dist-info/licenses/LICENSE
skyforge_mcp-0.1.0.dist-info/METADATA
skyforge_mcp-0.1.0.dist-info/WHEEL
skyforge_mcp-0.1.0.dist-info/entry_points.txt
skyforge_mcp-0.1.0.dist-info/top_level.txt
skyforge_mcp-0.1.0.dist-info/RECORD
