Metadata-Version: 2.4
Name: skyforge-mcp
Version: 0.1.0
Summary: SkyForge MCP Server - Model Context Protocol server for SkySpark/Haxall/Haystack systems
Author: James Gessel
License: MIT
Keywords: mcp,skyforge,skyspark,haxall,building,automation,iot
Classifier: Development Status :: 3 - Alpha
Classifier: Intended Audience :: Developers
Classifier: License :: OSI Approved :: MIT License
Classifier: Programming Language :: Python :: 3
Classifier: Programming Language :: Python :: 3.12
Requires-Python: >=3.12
License-File: LICENSE
Requires-Dist: httpx>=0.27.0
Requires-Dist: mcp[cli]>=1.16.0
Requires-Dist: phable>=0.1.20
Requires-Dist: pydantic>=2.12.0
Requires-Dist: python-dotenv>=1.0.0
Requires-Dist: starlette>=0.48.0
Requires-Dist: tzdata>=2025.2
Requires-Dist: uvicorn>=0.37.0
Requires-Dist: watchfiles>=0.24.0
Provides-Extra: dev
Requires-Dist: pytest>=8.0.0; extra == "dev"
Requires-Dist: pytest-asyncio>=0.23.0; extra == "dev"
Requires-Dist: pytest-mock>=3.12.0; extra == "dev"
Requires-Dist: pytest-cov>=4.1.0; extra == "dev"
Dynamic: license-file
